LICENSE
MANIFEST.in
README.rst
setup.cfg
setup.py
versioneer.py
artellapipe/__init__.py
artellapipe/tools/__init__.py
artellapipe/tools/modelchecker/__init__.py
artellapipe/tools/modelchecker/__logging__.ini
artellapipe/tools/modelchecker/__version__.py
artellapipe/tools/modelchecker/_version.py
artellapipe/tools/modelchecker/core/__init__.py
artellapipe/tools/modelchecker/core/modelchecker.py
artellapipe/tools/modelchecker/resources/images/modelchecker_logo.png
artellapipe/tools/modelchecker/widgets/__init__.py
artellapipe/tools/modelchecker/widgets/modelchecker.py
artellapipe_tools_modelchecker.egg-info/PKG-INFO
artellapipe_tools_modelchecker.egg-info/SOURCES.txt
artellapipe_tools_modelchecker.egg-info/dependency_links.txt
artellapipe_tools_modelchecker.egg-info/not-zip-safe
artellapipe_tools_modelchecker.egg-info/requires.txt
artellapipe_tools_modelchecker.egg-info/top_level.txt
tests/__init__.py
tests/test_general.py