Metadata-Version: 2.1
Name: artellapipe-tools-modelchecker
Version: 0.0.4
Summary: Tool to execute modeling checks for geometry
Home-page: https://github.com/ArtellaPipe/artellapipe-tools-modelchecker
Author: Tomas Poveda
Author-email: tpovedatd@gmail.com
License: MIT
Platform: UNKNOWN
Provides-Extra: dev
Provides-Extra: test
